FISHPainter/__init__.py
FISHPainter/src/__init__.py
FISHPainter/src/preprocess.py
FISHPainter/src/process_boxes.py
FISHPainter/src/signals.py
FISHPainter/src/datasets/__init__.py
FISHPainter/src/datasets/create.py
FISHPainter/src/datasets/ids.py
FISHPainter/src/utils/BackgroundTransformer.py
FISHPainter/src/utils/__init__.py
FISHPainter/src/utils/utils.py
FISHPainter/src/utils/zenodo_download.py
FISHPainter-2.2.dist-info/METADATA
FISHPainter-2.2.dist-info/WHEEL
FISHPainter-2.2.dist-info/top_level.txt
FISHPainter-2.2.dist-info/RECORD
