Metadata-Version: 2.1
Name: FISHPainter
Version: 2.2
Home-page: https://github.com/SimonBon/FISHPainter
Author: Simon Gutwein
Author-email: simon.gutwein@ccri.at
License: MIT
Classifier: License :: OSI Approved :: MIT License
Classifier: Programming Language :: Python
Classifier: Programming Language :: Python :: 3
Classifier: Programming Language :: Python :: 3.9
Requires-Dist: aiohttp ==3.8.5
Requires-Dist: aiosignal ==1.3.1
Requires-Dist: anyio ==3.7.1
Requires-Dist: arrow ==1.2.3
Requires-Dist: asttokens ==2.2.1
Requires-Dist: async-timeout ==4.0.3
Requires-Dist: backcall ==0.2.0
Requires-Dist: backoff ==2.2.1
Requires-Dist: blessed ==1.20.0
Requires-Dist: CacheControl ==0.13.1
Requires-Dist: CellPatchExtraction ==1.17
Requires-Dist: cellplot ==1.7
Requires-Dist: cellpose ==2.2.3
Requires-Dist: cellshape-cloud ==0.1.3
Requires-Dist: cellshape-helper ==0.0.18
Requires-Dist: certifi ==2024.2.2
Requires-Dist: charset-normalizer ==3.3.2
Requires-Dist: cleo ==2.0.1
Requires-Dist: cmake ==3.28.3
Requires-Dist: colorama ==0.4.6
Requires-Dist: comm ==0.1.4
Requires-Dist: contourpy ==1.2.0
Requires-Dist: coverage ==7.3.1
Requires-Dist: crashtest ==0.4.1
Requires-Dist: croniter ==1.4.1
Requires-Dist: csbdeep ==0.7.4
Requires-Dist: cycler ==0.12.1
Requires-Dist: DateTime ==5.2
Requires-Dist: dateutils ==0.6.12
Requires-Dist: debugpy ==1.6.6
Requires-Dist: decorator ==5.1.1
Requires-Dist: deepdiff ==6.5.0
Requires-Dist: distlib ==0.3.7
Requires-Dist: dulwich ==0.21.6
Requires-Dist: entrypoints ==0.4
Requires-Dist: exceptiongroup ==1.1.3
Requires-Dist: executing ==1.2.0
Requires-Dist: fastapi ==0.103.1
Requires-Dist: fastremap ==1.14.1
Requires-Dist: filelock ==3.13.1
Requires-Dist: fonttools ==4.49.0
Requires-Dist: frozenlist ==1.4.0
Requires-Dist: fsspec ==2024.2.0
Requires-Dist: h11 ==0.14.0
Requires-Dist: h5py ==3.10.0
Requires-Dist: idna ==3.6
Requires-Dist: imagecodecs ==2024.1.1
Requires-Dist: importlib-metadata ==6.8.0
Requires-Dist: importlib-resources ==6.1.3
Requires-Dist: inquirer ==3.1.3
Requires-Dist: installer ==0.7.0
Requires-Dist: ipykernel ==6.21.1
Requires-Dist: jaraco.classes ==3.3.0
Requires-Dist: jedi ==0.18.2
Requires-Dist: Jinja2 ==3.1.3
Requires-Dist: jupyter-client ==8.0.2
Requires-Dist: jupyter-core ==5.2.0
Requires-Dist: KapoorLabs-Lightning ==5.3.0
Requires-Dist: keyring ==24.2.0
Requires-Dist: kiwisolver ==1.4.5
Requires-Dist: lightning ==2.0.8
Requires-Dist: lightning-cloud ==0.5.38
Requires-Dist: lightning-utilities ==0.9.0
Requires-Dist: lit ==17.0.6
Requires-Dist: llvmlite ==0.42.0
Requires-Dist: MarkupSafe ==2.1.5
Requires-Dist: matplotlib ==3.8.3
Requires-Dist: matplotlib-inline ==0.1.6
Requires-Dist: mpmath ==1.3.0
Requires-Dist: multidict ==6.0.4
Requires-Dist: napatrackmater ==4.2.1
Requires-Dist: natsort ==8.4.0
Requires-Dist: nest-asyncio ==1.5.6
Requires-Dist: networkx ==3.2.1
Requires-Dist: numba ==0.59.0
Requires-Dist: numpy ==1.26.4
Requires-Dist: nvidia-cublas-cu11 ==11.10.3.66
Requires-Dist: nvidia-cublas-cu12 ==12.1.3.1
Requires-Dist: nvidia-cuda-cupti-cu11 ==11.7.101
Requires-Dist: nvidia-cuda-cupti-cu12 ==12.1.105
Requires-Dist: nvidia-cuda-nvrtc-cu11 ==11.7.99
Requires-Dist: nvidia-cuda-nvrtc-cu12 ==12.1.105
Requires-Dist: nvidia-cuda-runtime-cu11 ==11.7.99
Requires-Dist: nvidia-cuda-runtime-cu12 ==12.1.105
Requires-Dist: nvidia-cudnn-cu11 ==8.5.0.96
Requires-Dist: nvidia-cudnn-cu12 ==8.9.2.26
Requires-Dist: nvidia-cufft-cu11 ==10.9.0.58
Requires-Dist: nvidia-cufft-cu12 ==11.0.2.54
Requires-Dist: nvidia-curand-cu11 ==10.2.10.91
Requires-Dist: nvidia-curand-cu12 ==10.3.2.106
Requires-Dist: nvidia-cusolver-cu11 ==11.4.0.1
Requires-Dist: nvidia-cusolver-cu12 ==11.4.5.107
Requires-Dist: nvidia-cusparse-cu11 ==11.7.4.91
Requires-Dist: nvidia-cusparse-cu12 ==12.1.0.106
Requires-Dist: nvidia-nccl-cu11 ==2.14.3
Requires-Dist: nvidia-nccl-cu12 ==2.19.3
Requires-Dist: nvidia-nvjitlink-cu12 ==12.4.99
Requires-Dist: nvidia-nvtx-cu11 ==11.7.91
Requires-Dist: nvidia-nvtx-cu12 ==12.1.105
Requires-Dist: opencv-python ==4.9.0.80
Requires-Dist: opencv-python-headless ==4.9.0.80
Requires-Dist: parso ==0.8.3
Requires-Dist: pathlib ==1.0.1
Requires-Dist: pexpect ==4.8.0
Requires-Dist: pickleshare ==0.7.5
Requires-Dist: pillow ==10.2.0
Requires-Dist: pkginfo ==1.9.6
Requires-Dist: platformdirs ==3.10.0
Requires-Dist: pluggy ==1.3.0
Requires-Dist: poetry ==1.6.1
Requires-Dist: poetry-core ==1.7.0
Requires-Dist: poetry-plugin-export ==1.5.0
Requires-Dist: ptyprocess ==0.7.0
Requires-Dist: pure-eval ==0.2.2
Requires-Dist: pyaml ==23.12.0
Requires-Dist: Pygments ==2.14.0
Requires-Dist: pynndescent ==0.5.10
Requires-Dist: pyntcloud ==0.3.1
Requires-Dist: pyparsing ==3.1.2
Requires-Dist: pyproject-api ==1.6.1
Requires-Dist: pytest ==7.4.2
Requires-Dist: pytest-cov ==4.1.0
Requires-Dist: python-editor ==1.0.4
Requires-Dist: python-multipart ==0.0.6
Requires-Dist: pytorch-lightning ==2.0.8
Requires-Dist: PyYAML ==6.0.1
Requires-Dist: pyzmq ==25.0.0
Requires-Dist: rapidfuzz ==2.15.1
Requires-Dist: readchar ==4.0.5
Requires-Dist: requests ==2.31.0
Requires-Dist: requests-toolbelt ==1.0.0
Requires-Dist: roifile ==2024.1.10
Requires-Dist: scipy ==1.12.0
Requires-Dist: shellingham ==1.5.3
Requires-Dist: stack-data ==0.6.2
Requires-Dist: stardist ==0.8.5
Requires-Dist: starlette ==0.27.0
Requires-Dist: starsessions ==1.3.0
Requires-Dist: sympy ==1.12
Requires-Dist: test-tube ==0.7.5
Requires-Dist: tifffile ==2024.2.12
Requires-Dist: tomlkit ==0.12.1
Requires-Dist: torch ==2.0.1
Requires-Dist: torchmetrics ==1.1.2
Requires-Dist: torchvision ==0.17.1
Requires-Dist: tornado ==6.2
Requires-Dist: tox ==4.11.3
Requires-Dist: tqdm ==4.66.2
Requires-Dist: traitlets ==5.9.0
Requires-Dist: trimesh ==3.23.5
Requires-Dist: triton ==2.0.0
Requires-Dist: trove-classifiers ==2023.8.7
Requires-Dist: urllib3 ==2.2.1
Requires-Dist: uvicorn ==0.23.2
Requires-Dist: virtualenv ==20.24.5
Requires-Dist: vollseg ==32.1.9
Requires-Dist: wcwidth ==0.2.6
Requires-Dist: websocket-client ==1.6.3
Requires-Dist: websockets ==11.0.3
Requires-Dist: yarl ==1.9.2
